{
"type": "FeatureCollection",
"name": "69_bravo_location",
"crs": { "type": "name", "properties": { "name": "urn:ogc:def:crs:OGC:1.3:CRS84" } },
"features": [
{ "type": "Feature", "properties": { }, "geometry": { "type": "Point", "coordinates": [ -118.627420663833618, 34.074959215300794 ] } }
]
}
